{"title":"Dirty Flix - Tattooed nerdy chick fucked good sex","uid":13958393,"size":128605512,"categoryP":"porn","categoryS":"movie_clips","magnet":"?xt=urn:btih:0248add1e4c118a7234e65be4b5635af581a0b7e&amp;dn=Dirty+Flix+-+Tattooed+nerdy+chick+fucked+good+sex&amp;tr=udp%3A%2F%2Ftracker.leechers-paradise.org%3A6969&amp;tr=udp%3A%2F%2Fzer0day.ch%3A1337&amp;tr=udp%3A%2F%2Fopen.demonii.com%3A1337&amp;tr=udp%3A%2F%2Ftracker.coppersurfer.tk%3A6969&amp;tr=udp%3A%2F%2Fexodus.desync.com%3A6969","seeders":0,"leechers":1,"uploader":"demonoidt","files":1,"time":1458561434,"description":"Samples\r\n \nhttp://demonoid.co/2016/03/21/dirty-flix-tattooed-nerdy-chick-fucked-good-sex/\r\n \nhttp://adultwallpapers.co.in/dirty-flix-tattooed-nerdy-chick-fucked-good-sex/","torrent":{"xt":"urn:btih:0248add1e4c118a7234e65be4b5635af581a0b7e","amp;dn":"Dirty+Flix+-+Tattooed+nerdy+chick+fucked+good+sex","amp;tr":["udp%3A%2F%2Ftracker.leechers-paradise.org%3A6969","udp%3A%2F%2Fzer0day.ch%3A1337","udp%3A%2F%2Fopen.demonii.com%3A1337","udp%3A%2F%2Ftracker.coppersurfer.tk%3A6969","udp%3A%2F%2Fexodus.desync.com%3A6969"],"infoHash":"0248add1e4c118a7234e65be4b5635af581a0b7e","infoHashBuffer":{"type":"Buffer","data":[2,72,173,209,228,193,24,167,35,78,101,190,75,86,53,175,88,26,11,126]},"announce":[],"urlList":[]}}