{"title":"Murmur.of.the.Hearts.2015.Chinese.1080p.BluRay.x264.AAC-DDL","uid":13648683,"size":2071597861,"categoryP":"video","categoryS":"hd___movies","magnet":"?xt=urn:btih:0a25f903dd7f939231978ae8340f19d703ed8371&amp;dn=Murmur.of.the.Hearts.2015.Chinese.1080p.BluRay.x264.AAC-DDL&amp;tr=udp%3A%2F%2Ftracker.leechers-paradise.org%3A6969&amp;tr=udp%3A%2F%2Fzer0day.ch%3A1337&amp;tr=udp%3A%2F%2Fopen.demonii.com%3A1337&amp;tr=udp%3A%2F%2Ftracker.coppersurfer.tk%3A6969&amp;tr=udp%3A%2F%2Fexodus.desync.com%3A6969","seeders":0,"leechers":0,"uploader":".BONE.","files":3,"time":1456183617,"description":"StoryLine\r\n\r\nAn artist reunites with her brother after the two were separated years ago when she left Liudau, an island off of Taiwan. \r\n\r\nGeneral\r\n\r\nFormat.......: MP4\r\nFile Size....: 1.91 GB\r\nDuration.....:1hr 59min\r\nBitrate......: 2300\r\nSource.......: BLURAY\r\nEncoder&quot;.......DDL\r\nSAMPLE......... YESS\r\nSubtitles....: Englsih (External.SRT)\r\n \nhttp://www.imdb.com/title/tt4484426/\r\n\r\nVideo\r\n\r\nVideo Format......: AVC\r\nVideo Codec.......: x264 core 148 r2638 7599210\r\nBitrate...........: 2300 Kbps\r\nFrame Rate........: 23.976 fps\r\nWidth.............: 1920 pixels\r\nHeight............: 1080 pixels\r\naspect ratio......: 16:9\r\n\r\n\r\nAudio #1:\r\n\r\nFormat..........: AAC\r\nBitrate.........: 96 Kbps\r\nChannels........: 2 channels\r\nSampling Rate...: 48.0 KHz\r\nLanguage........: CHINESE(","torrent":{"xt":"urn:btih:0a25f903dd7f939231978ae8340f19d703ed8371","amp;dn":"Murmur.of.the.Hearts.2015.Chinese.1080p.BluRay.x264.AAC-DDL","amp;tr":["udp%3A%2F%2Ftracker.leechers-paradise.org%3A6969","udp%3A%2F%2Fzer0day.ch%3A1337","udp%3A%2F%2Fopen.demonii.com%3A1337","udp%3A%2F%2Ftracker.coppersurfer.tk%3A6969","udp%3A%2F%2Fexodus.desync.com%3A6969"],"infoHash":"0a25f903dd7f939231978ae8340f19d703ed8371","infoHashBuffer":{"type":"Buffer","data":[10,37,249,3,221,127,147,146,49,151,138,232,52,15,25,215,3,237,131,113]},"announce":[],"urlList":[]}}