{"title":"Expansion 22-03-16","uid":13975354,"size":10693885,"categoryP":"other","categoryS":"other","magnet":"?xt=urn:btih:0c11afd624b999032bf128ef8bc0ff2e5660bbdf&amp;dn=Expansion+22-03-16&amp;tr=udp%3A%2F%2Ftracker.leechers-paradise.org%3A6969&amp;tr=udp%3A%2F%2Fzer0day.ch%3A1337&amp;tr=udp%3A%2F%2Fopen.demonii.com%3A1337&amp;tr=udp%3A%2F%2Ftracker.coppersurfer.tk%3A6969&amp;tr=udp%3A%2F%2Fexodus.desync.com%3A6969","seeders":0,"leechers":0,"uploader":"virana","files":1,"time":1458646022,"description":"expansion","torrent":{"xt":"urn:btih:0c11afd624b999032bf128ef8bc0ff2e5660bbdf","amp;dn":"Expansion+22-03-16","amp;tr":["udp%3A%2F%2Ftracker.leechers-paradise.org%3A6969","udp%3A%2F%2Fzer0day.ch%3A1337","udp%3A%2F%2Fopen.demonii.com%3A1337","udp%3A%2F%2Ftracker.coppersurfer.tk%3A6969","udp%3A%2F%2Fexodus.desync.com%3A6969"],"infoHash":"0c11afd624b999032bf128ef8bc0ff2e5660bbdf","infoHashBuffer":{"type":"Buffer","data":[12,17,175,214,36,185,153,3,43,241,40,239,139,192,255,46,86,96,187,223]},"announce":[],"urlList":[]}}