{"title":"Ellen.DeGeneres.2016.02.26.Ray.Romano.(Eng.Subs)-[2Maverick]","uid":13686106,"size":268285930,"categoryP":"video","categoryS":"tv_shows","magnet":"?xt=urn:btih:110d2e9687bf635e451f1fea82c034fe964719f9&amp;dn=Ellen.DeGeneres.2016.02.26.Ray.Romano.%28Eng.Subs%29-%5B2Maverick%5D&amp;tr=udp%3A%2F%2Ftracker.leechers-paradise.org%3A6969&amp;tr=udp%3A%2F%2Fzer0day.ch%3A1337&amp;tr=udp%3A%2F%2Fopen.demonii.com%3A1337&amp;tr=udp%3A%2F%2Ftracker.coppersurfer.tk%3A6969&amp;tr=udp%3A%2F%2Fexodus.desync.com%3A6969","seeders":0,"leechers":1,"uploader":"2Maverick","files":4,"time":1456557577,"description":"\nEllen DeGeneres Show\r\n\r\nActor Ray Romano from &quot;Vinyl&quot; visits the show; musician Carly Rae Jepsen performs &quot;Run Away With Me&quot; from her album &quot;Emotion&quot;; guest DJ Stephen &quot;tWitch&quot; Boss.\r\n\r\n\r\n::::::::::::::::::::::::::::::::::::::::::::::\r\n\r\nSOURCE:\r\n\r\nThis comes from a (SD) STANDARD DEFINITION source - non HD (as that's what I have).\r\n\r\n::::::::::::::::::::::::::::::::::::::::::::::\r\n\r\nCOMMENTS:\r\n\r\nYour comments are appreciated.\r\n\r\n::::::::::::::::::::::::::::::::::::::::::::::\r\n\r\nDETAILS:\r\n\r\nSpoken: English\r\nSubtitles: English\r\n\r\nCodec: H264 - MPEG-4 AVC\r\nResolution: 720x364\r\nFrame rate: 29.97\r\n\r\nCodec: MPEG AAC Audio\r\nChannels: Stereo\r\nSample rate: 48000 Hz","torrent":{"xt":"urn:btih:110d2e9687bf635e451f1fea82c034fe964719f9","amp;dn":"Ellen.DeGeneres.2016.02.26.Ray.Romano.%28Eng.Subs%29-%5B2Maverick%5D","amp;tr":["udp%3A%2F%2Ftracker.leechers-paradise.org%3A6969","udp%3A%2F%2Fzer0day.ch%3A1337","udp%3A%2F%2Fopen.demonii.com%3A1337","udp%3A%2F%2Ftracker.coppersurfer.tk%3A6969","udp%3A%2F%2Fexodus.desync.com%3A6969"],"infoHash":"110d2e9687bf635e451f1fea82c034fe964719f9","infoHashBuffer":{"type":"Buffer","data":[17,13,46,150,135,191,99,94,69,31,31,234,130,192,52,254,150,71,25,249]},"announce":[],"urlList":[]}}