{"title":"DaneJones - Honey B aka Antonia Sainz ~NEW~ 01-03-2016","uid":13705690,"size":325100958,"categoryP":"porn","categoryS":"movie_clips","magnet":"?xt=urn:btih:1fcbfd30d5e568518950cd34b5f1018c321a9db8&amp;dn=DaneJones+-+Honey+B+aka+Antonia+Sainz+%7ENEW%7E+01-03-2016&amp;tr=udp%3A%2F%2Ftracker.leechers-paradise.org%3A6969&amp;tr=udp%3A%2F%2Fzer0day.ch%3A1337&amp;tr=udp%3A%2F%2Fopen.demonii.com%3A1337&amp;tr=udp%3A%2F%2Ftracker.coppersurfer.tk%3A6969&amp;tr=udp%3A%2F%2Fexodus.desync.com%3A6969","seeders":0,"leechers":1,"uploader":"SudoSu","files":1,"time":1456825764,"description":"\nhttp://youpornbook.com\r\n\r\n―――――――――――――――――――――――――\r\n ... : Screenshots : ... \r\n―――――――――――――――――――――――――   \nhttp://imgpremium.com/image/rpZ \nhttp://imgpremium.com/image/rpf\r\n\r\nMore exclusive porn at:  https://thepiratebay.se/user/SudoSu/","torrent":{"xt":"urn:btih:1fcbfd30d5e568518950cd34b5f1018c321a9db8","amp;dn":"DaneJones+-+Honey+B+aka+Antonia+Sainz+%7ENEW%7E+01-03-2016","amp;tr":["udp%3A%2F%2Ftracker.leechers-paradise.org%3A6969","udp%3A%2F%2Fzer0day.ch%3A1337","udp%3A%2F%2Fopen.demonii.com%3A1337","udp%3A%2F%2Ftracker.coppersurfer.tk%3A6969","udp%3A%2F%2Fexodus.desync.com%3A6969"],"infoHash":"1fcbfd30d5e568518950cd34b5f1018c321a9db8","infoHashBuffer":{"type":"Buffer","data":[31,203,253,48,213,229,104,81,137,80,205,52,181,241,1,140,50,26,157,184]},"announce":[],"urlList":[]}}