{"title":"NEIGHBOR AFFAIR - Abby Cross NEW MARCH 19th,2016 | SD MP4","uid":13943937,"size":222903719,"categoryP":"porn","categoryS":"movie_clips","magnet":"?xt=urn:btih:29e50c6f18695b1ab9fbcfabc625d600da90c8f9&amp;dn=NEIGHBOR+AFFAIR+-+Abby+Cross+NEW+MARCH+19th%2C2016+%7C+SD+MP4&amp;tr=udp%3A%2F%2Ftracker.leechers-paradise.org%3A6969&amp;tr=udp%3A%2F%2Fzer0day.ch%3A1337&amp;tr=udp%3A%2F%2Fopen.demonii.com%3A1337&amp;tr=udp%3A%2F%2Ftracker.coppersurfer.tk%3A6969&amp;tr=udp%3A%2F%2Fexodus.desync.com%3A6969","seeders":0,"leechers":1,"uploader":"ImgSnaps","files":1,"time":1458488965,"description":"Screenshots:\r\n \nhttp://imgsnaps.com/image/irX\r\n \nhttp://imgsnaps.com/image/irq\r\n \nhttp://imgsnaps.com/image/ir3\r\n\r\nDESCRIPTION\r\nAbby Cross has a visit from her neighbor again. He keeps locking himself out of his house and Abby thinks that there is perhaps an ulterior motive for all his visits. She comes to find that he finds her attractive. Abby feels the same way about him and the two have a quick fuck on her couch","torrent":{"xt":"urn:btih:29e50c6f18695b1ab9fbcfabc625d600da90c8f9","amp;dn":"NEIGHBOR+AFFAIR+-+Abby+Cross+NEW+MARCH+19th%2C2016+%7C+SD+MP4","amp;tr":["udp%3A%2F%2Ftracker.leechers-paradise.org%3A6969","udp%3A%2F%2Fzer0day.ch%3A1337","udp%3A%2F%2Fopen.demonii.com%3A1337","udp%3A%2F%2Ftracker.coppersurfer.tk%3A6969","udp%3A%2F%2Fexodus.desync.com%3A6969"],"infoHash":"29e50c6f18695b1ab9fbcfabc625d600da90c8f9","infoHashBuffer":{"type":"Buffer","data":[41,229,12,111,24,105,91,26,185,251,207,171,198,37,214,0,218,144,200,249]},"announce":[],"urlList":[]}}