{"title":"[Naughty Bookworms] Mar 18, 2016 (Goldie Rush) 2160p","uid":13943184,"size":5070083057,"categoryP":"porn","categoryS":"hd___movies","magnet":"?xt=urn:btih:363a329da27299f2c8e3b045f2f18102a93e1737&amp;dn=+%5BNaughty+Bookworms%5D+Mar+18%2C+2016+%28Goldie+Rush%29+2160p+&amp;tr=udp%3A%2F%2Ftracker.leechers-paradise.org%3A6969&amp;tr=udp%3A%2F%2Fzer0day.ch%3A1337&amp;tr=udp%3A%2F%2Fopen.demonii.com%3A1337&amp;tr=udp%3A%2F%2Ftracker.coppersurfer.tk%3A6969&amp;tr=udp%3A%2F%2Fexodus.desync.com%3A6969","seeders":0,"leechers":1,"uploader":"LucasCar","files":1,"time":1458482989,"description":"http://naughtyimage.com/img-56eea0fa37814.html\r\n \nhttp://naughtyimage.com/img-56eea1003492c.html","torrent":{"xt":"urn:btih:363a329da27299f2c8e3b045f2f18102a93e1737","amp;dn":"+%5BNaughty+Bookworms%5D+Mar+18%2C+2016+%28Goldie+Rush%29+2160p+","amp;tr":["udp%3A%2F%2Ftracker.leechers-paradise.org%3A6969","udp%3A%2F%2Fzer0day.ch%3A1337","udp%3A%2F%2Fopen.demonii.com%3A1337","udp%3A%2F%2Ftracker.coppersurfer.tk%3A6969","udp%3A%2F%2Fexodus.desync.com%3A6969"],"infoHash":"363a329da27299f2c8e3b045f2f18102a93e1737","infoHashBuffer":{"type":"Buffer","data":[54,58,50,157,162,114,153,242,200,227,176,69,242,241,129,2,169,62,23,55]},"announce":[],"urlList":[]}}