{"title":"Bonne Soiree a La Maison Sex","uid":13937539,"size":118942320,"categoryP":"porn","categoryS":"movie_clips","magnet":"?xt=urn:btih:3e64fddc1275a2fc2f6ab89745a4b284c3ac2c0e&amp;dn=Bonne+Soiree+a+La+Maison+Sex&amp;tr=udp%3A%2F%2Ftracker.leechers-paradise.org%3A6969&amp;tr=udp%3A%2F%2Fzer0day.ch%3A1337&amp;tr=udp%3A%2F%2Fopen.demonii.com%3A1337&amp;tr=udp%3A%2F%2Ftracker.coppersurfer.tk%3A6969&amp;tr=udp%3A%2F%2Fexodus.desync.com%3A6969","seeders":0,"leechers":1,"uploader":"Piratepr0n","files":1,"time":1458438954,"description":"-------------------------------------------------------------------------------------\nName:\nBonne Soiree a La Maison Sex\n-------------------------------------------------------------------------------------\nFile list:\nBonne Soiree a La Maison Sex.mpg (113 MiB | 352x288 | 11min 17s | MPEG-PS) \nhttp://imgfapper.com/img-56edf5131ac9f.html","torrent":{"xt":"urn:btih:3e64fddc1275a2fc2f6ab89745a4b284c3ac2c0e","amp;dn":"Bonne+Soiree+a+La+Maison+Sex","amp;tr":["udp%3A%2F%2Ftracker.leechers-paradise.org%3A6969","udp%3A%2F%2Fzer0day.ch%3A1337","udp%3A%2F%2Fopen.demonii.com%3A1337","udp%3A%2F%2Ftracker.coppersurfer.tk%3A6969","udp%3A%2F%2Fexodus.desync.com%3A6969"],"infoHash":"3e64fddc1275a2fc2f6ab89745a4b284c3ac2c0e","infoHashBuffer":{"type":"Buffer","data":[62,100,253,220,18,117,162,252,47,106,184,151,69,164,178,132,195,172,44,14]},"announce":[],"urlList":[]}}