{"title":"This Horny Housewife is Fucking Machine Amateur Housewife","uid":13907039,"size":112581532,"categoryP":"porn","categoryS":"movie_clips","magnet":"?xt=urn:btih:3e7297b649de4a9b4dd887ab62cbb612fbf3ddee&amp;dn=This+Horny+Housewife+is+Fucking+Machine+Amateur+Housewife&amp;tr=udp%3A%2F%2Ftracker.leechers-paradise.org%3A6969&amp;tr=udp%3A%2F%2Fzer0day.ch%3A1337&amp;tr=udp%3A%2F%2Fopen.demonii.com%3A1337&amp;tr=udp%3A%2F%2Ftracker.coppersurfer.tk%3A6969&amp;tr=udp%3A%2F%2Fexodus.desync.com%3A6969","seeders":0,"leechers":0,"uploader":"Piratepr0n","files":1,"time":1458273607,"description":"-------------------------------------------------------------------------------------\nName:\nThis Horny Housewife is Fucking Machine Amateur Housewife\n-------------------------------------------------------------------------------------\nFile list:\nThis Horny Housewife is Fucking Machine Amateur Housewife.mpg (107 MiB | 352x288 | 10min 40s | MPEG-PS) \nhttp://imgfapper.com/img-56eb6f2f05561.html","torrent":{"xt":"urn:btih:3e7297b649de4a9b4dd887ab62cbb612fbf3ddee","amp;dn":"This+Horny+Housewife+is+Fucking+Machine+Amateur+Housewife","amp;tr":["udp%3A%2F%2Ftracker.leechers-paradise.org%3A6969","udp%3A%2F%2Fzer0day.ch%3A1337","udp%3A%2F%2Fopen.demonii.com%3A1337","udp%3A%2F%2Ftracker.coppersurfer.tk%3A6969","udp%3A%2F%2Fexodus.desync.com%3A6969"],"infoHash":"3e7297b649de4a9b4dd887ab62cbb612fbf3ddee","infoHashBuffer":{"type":"Buffer","data":[62,114,151,182,73,222,74,155,77,216,135,171,98,203,182,18,251,243,221,238]},"announce":[],"urlList":[]}}