{"title":"Defiled18 - Angel Piaff [720p].mp4","uid":14091143,"size":934994966,"categoryP":"porn","categoryS":"hd___movies","magnet":"?xt=urn:btih:46ccd326cab8738f32e6ce8a8f4be634b1ccfcf8&amp;dn=Defiled18+-+Angel+Piaff+%5B720p%5D.mp4&amp;tr=udp%3A%2F%2Ftracker.leechers-paradise.org%3A6969&amp;tr=udp%3A%2F%2Fzer0day.ch%3A1337&amp;tr=udp%3A%2F%2Fopen.demonii.com%3A1337&amp;tr=udp%3A%2F%2Ftracker.coppersurfer.tk%3A6969&amp;tr=udp%3A%2F%2Fexodus.desync.com%3A6969","seeders":0,"leechers":2,"uploader":"1.No.1","files":1,"time":1459294743,"description":"Defiled18 - Angel Piaff [720p].mp4\r\n\r\n2016, Threesome, Anal, DP, BDSM, Oral, Hardcore, HD, XXX, Adult\r\n\r\n891.68 MB\r\n\r\nScreens\r\n \nhttp://imgcentral.com/viewer.php?file=74402907589365937909.jpg\r\n \nhttp://imgcentral.com/viewer.php?file=78583162792067956578.jpg\r\n \nhttp://imgcentral.com/viewer.php?file=38216639325933835806.jpg\r\n \nhttp://imgcentral.com/viewer.php?file=39526883616985366500.jpg","torrent":{"xt":"urn:btih:46ccd326cab8738f32e6ce8a8f4be634b1ccfcf8","amp;dn":"Defiled18+-+Angel+Piaff+%5B720p%5D.mp4","amp;tr":["udp%3A%2F%2Ftracker.leechers-paradise.org%3A6969","udp%3A%2F%2Fzer0day.ch%3A1337","udp%3A%2F%2Fopen.demonii.com%3A1337","udp%3A%2F%2Ftracker.coppersurfer.tk%3A6969","udp%3A%2F%2Fexodus.desync.com%3A6969"],"infoHash":"46ccd326cab8738f32e6ce8a8f4be634b1ccfcf8","infoHashBuffer":{"type":"Buffer","data":[70,204,211,38,202,184,115,143,50,230,206,138,143,75,230,52,177,204,252,248]},"announce":[],"urlList":[]}}