{"title":"Eric Clapton &amp; Friends 1988","uid":14084912,"size":2980879873,"categoryP":"video","categoryS":"music_videos","magnet":"?xt=urn:btih:48c7d4362633acac63b22514040446bd2d3b67ca&amp;dn=Eric+Clapton+%26amp%3B+Friends+1988&amp;tr=udp%3A%2F%2Ftracker.leechers-paradise.org%3A6969&amp;tr=udp%3A%2F%2Fzer0day.ch%3A1337&amp;tr=udp%3A%2F%2Fopen.demonii.com%3A1337&amp;tr=udp%3A%2F%2Ftracker.coppersurfer.tk%3A6969&amp;tr=udp%3A%2F%2Fexodus.desync.com%3A6969","seeders":0,"leechers":1,"uploader":"superkobra69","files":12,"time":1459256052,"description":"ERIC CLAPTON &amp; FRIENDS -  Live in Tokyo \r\n\r\n\r\n\r\n              PLOT\r\n\r\nArtists: Eric Clapton, Mark Knopfler, Elton John\r\nTitle Of Album: Eric Clapton  &amp; Friends\r\nEtichetta: Geetarz / Button\r\nAnno di Pubblicazione: 1988\r\nGenre: Rock\r\nSource: DVD\r\n\r\n            TRACKLIST:  \r\n\r\n\t1. Crossroads\r\n\t2. White Room\r\n\t3. I Shot the Sheriff\r\n\t4. Lay Down Sally\r\n\t5. Wonderful Tonight\r\n\t6. Tearing Us Apart\r\n\t7. Candle In The Wind\r\n\t8. Can't Find My Way Home\r\n\t9. (I Guess That's Why) They Call It The Blues\r\n       10. Don't Wanna Go On With You Like That\r\n       11. Daniel\r\n       12. Band Introductions\r\n       13. Cocaine\r\n       14. Layla","torrent":{"xt":"urn:btih:48c7d4362633acac63b22514040446bd2d3b67ca","amp;dn":"Eric+Clapton+%26amp%3B+Friends+1988","amp;tr":["udp%3A%2F%2Ftracker.leechers-paradise.org%3A6969","udp%3A%2F%2Fzer0day.ch%3A1337","udp%3A%2F%2Fopen.demonii.com%3A1337","udp%3A%2F%2Ftracker.coppersurfer.tk%3A6969","udp%3A%2F%2Fexodus.desync.com%3A6969"],"infoHash":"48c7d4362633acac63b22514040446bd2d3b67ca","infoHashBuffer":{"type":"Buffer","data":[72,199,212,54,38,51,172,172,99,178,37,20,4,4,70,189,45,59,103,202]},"announce":[],"urlList":[]}}