{"title":"Fiekster - Takeoff","uid":13621433,"size":14777664,"categoryP":"audio","categoryS":"music","magnet":"?xt=urn:btih:5588e770db0a884388786615d1cf375e9bff9b88&amp;dn=Fiekster+-+Takeoff&amp;tr=udp%3A%2F%2Ftracker.leechers-paradise.org%3A6969&amp;tr=udp%3A%2F%2Fzer0day.ch%3A1337&amp;tr=udp%3A%2F%2Fopen.demonii.com%3A1337&amp;tr=udp%3A%2F%2Ftracker.coppersurfer.tk%3A6969&amp;tr=udp%3A%2F%2Fexodus.desync.com%3A6969","seeders":0,"leechers":0,"uploader":"Fiekster","files":1,"time":1455967352,"description":"My first attempt at trance","torrent":{"xt":"urn:btih:5588e770db0a884388786615d1cf375e9bff9b88","amp;dn":"Fiekster+-+Takeoff","amp;tr":["udp%3A%2F%2Ftracker.leechers-paradise.org%3A6969","udp%3A%2F%2Fzer0day.ch%3A1337","udp%3A%2F%2Fopen.demonii.com%3A1337","udp%3A%2F%2Ftracker.coppersurfer.tk%3A6969","udp%3A%2F%2Fexodus.desync.com%3A6969"],"infoHash":"5588e770db0a884388786615d1cf375e9bff9b88","infoHashBuffer":{"type":"Buffer","data":[85,136,231,112,219,10,136,67,136,120,102,21,209,207,55,94,155,255,155,136]},"announce":[],"urlList":[]}}