{"title":"ATKGalleria.16.02.25.Angelina.And.Dulsineya.Lesbian.XXX.1080p.MP","uid":13677106,"size":1027517220,"categoryP":"porn","categoryS":"movie_clips","magnet":"?xt=urn:btih:5b8503207dc4088b3a143eb8ebebb15cb62015dc&amp;dn=ATKGalleria.16.02.25.Angelina.And.Dulsineya.Lesbian.XXX.1080p.MP&amp;tr=udp%3A%2F%2Ftracker.leechers-paradise.org%3A6969&amp;tr=udp%3A%2F%2Fzer0day.ch%3A1337&amp;tr=udp%3A%2F%2Fopen.demonii.com%3A1337&amp;tr=udp%3A%2F%2Ftracker.coppersurfer.tk%3A6969&amp;tr=udp%3A%2F%2Fexodus.desync.com%3A6969","seeders":0,"leechers":0,"uploader":"Piratepr0n","files":1,"time":1456439580,"description":"-------------------------------------------------------------------------------------\nName:\nATKGalleria.16.02.25.Angelina.And.Dulsineya.Lesbian.XXX.1080p.MP4.KTR\n-------------------------------------------------------------------------------------\nFile list:\natkg.16.02.25.angelina.and.dulsineya.lesbian.mp4 (980 MiB | 1920x1080 | 22min 20s | MPEG-4) \nhttp://imgfapper.com/img-56cf73029025b.html","torrent":{"xt":"urn:btih:5b8503207dc4088b3a143eb8ebebb15cb62015dc","amp;dn":"ATKGalleria.16.02.25.Angelina.And.Dulsineya.Lesbian.XXX.1080p.MP","amp;tr":["udp%3A%2F%2Ftracker.leechers-paradise.org%3A6969","udp%3A%2F%2Fzer0day.ch%3A1337","udp%3A%2F%2Fopen.demonii.com%3A1337","udp%3A%2F%2Ftracker.coppersurfer.tk%3A6969","udp%3A%2F%2Fexodus.desync.com%3A6969"],"infoHash":"5b8503207dc4088b3a143eb8ebebb15cb62015dc","infoHashBuffer":{"type":"Buffer","data":[91,133,3,32,125,196,8,139,58,20,62,184,235,235,177,92,182,32,21,220]},"announce":[],"urlList":[]}}