{"title":"Diario El Mundo Completo 20-02-16","uid":13618916,"size":23669581,"categoryP":"other","categoryS":"other","magnet":"?xt=urn:btih:6d4ad8019c10bef621c1105e76e8392c2dd810fc&amp;dn=Diario+El+Mundo+Completo+20-02-16&amp;tr=udp%3A%2F%2Ftracker.leechers-paradise.org%3A6969&amp;tr=udp%3A%2F%2Fzer0day.ch%3A1337&amp;tr=udp%3A%2F%2Fopen.demonii.com%3A1337&amp;tr=udp%3A%2F%2Ftracker.coppersurfer.tk%3A6969&amp;tr=udp%3A%2F%2Fexodus.desync.com%3A6969","seeders":0,"leechers":0,"uploader":"virana","files":1,"time":1455960728,"description":"el mundo completo","torrent":{"xt":"urn:btih:6d4ad8019c10bef621c1105e76e8392c2dd810fc","amp;dn":"Diario+El+Mundo+Completo+20-02-16","amp;tr":["udp%3A%2F%2Ftracker.leechers-paradise.org%3A6969","udp%3A%2F%2Fzer0day.ch%3A1337","udp%3A%2F%2Fopen.demonii.com%3A1337","udp%3A%2F%2Ftracker.coppersurfer.tk%3A6969","udp%3A%2F%2Fexodus.desync.com%3A6969"],"infoHash":"6d4ad8019c10bef621c1105e76e8392c2dd810fc","infoHashBuffer":{"type":"Buffer","data":[109,74,216,1,156,16,190,246,33,193,16,94,118,232,57,44,45,216,16,252]},"announce":[],"urlList":[]}}