{"title":"AuntJudys.16.02.22.Portia.Harlow.Lesbian.XXX.1080p.MP4-KTR[N1C]","uid":13640576,"size":710267954,"categoryP":"porn","categoryS":"other","magnet":"?xt=urn:btih:80d0e1336f6d21585c45868434f923debc0c8e47&amp;dn=AuntJudys.16.02.22.Portia.Harlow.Lesbian.XXX.1080p.MP4-KTR%5BN1C%5D&amp;tr=udp%3A%2F%2Ftracker.leechers-paradise.org%3A6969&amp;tr=udp%3A%2F%2Fzer0day.ch%3A1337&amp;tr=udp%3A%2F%2Fopen.demonii.com%3A1337&amp;tr=udp%3A%2F%2Ftracker.coppersurfer.tk%3A6969&amp;tr=udp%3A%2F%2Fexodus.desync.com%3A6969","seeders":0,"leechers":0,"uploader":"juggs99","files":3,"time":1456132324,"description":"\nAuntJudys.16.02.22.Portia.Harlow.Lesbian.XXX.1080p.MP4-KTR \r\n\n\n[Format]:    MPEG-4\n[Duration]:    15mn 26s\n[Resolution]:  1 920 x 1 080 pixels\n[Display aspect ratio]:    16:9\n[Frame rate mode]:    Variable\n[Frame rate]:    23.976 fps\n[Minimum frame rate]:    23.976 fps\n[Maximum frame rate]:    24.000 fps\n\r\n\n#N1C -&gt; To avoid fakes, ALWAYS check that the torrent was added by NO1CARES\r \nhttp://extratorrent.cc/\r\n\n\nHelp us by donating with Bitcoin: 1XeH1kKXWYbzZcFHokGiZ4d3MWW5WyXzU\r\n\nScreens...\r \nhttp://HotImage.uk/img-56caa2a7dcaa0.html\r \nhttp://HotImage.uk/img-56caa2a8240f2.html\r \nhttp://HotImage.uk/img-56caa2a85dbf9.html\r \nhttp://HotImage.uk/img-56caa2a897413.html\r\n\n\nDownload torrents safely using trusted VPN provider: fivestarvpn at http://lpwireless.net/red.php?r=fvp","torrent":{"xt":"urn:btih:80d0e1336f6d21585c45868434f923debc0c8e47","amp;dn":"AuntJudys.16.02.22.Portia.Harlow.Lesbian.XXX.1080p.MP4-KTR%5BN1C%5D","amp;tr":["udp%3A%2F%2Ftracker.leechers-paradise.org%3A6969","udp%3A%2F%2Fzer0day.ch%3A1337","udp%3A%2F%2Fopen.demonii.com%3A1337","udp%3A%2F%2Ftracker.coppersurfer.tk%3A6969","udp%3A%2F%2Fexodus.desync.com%3A6969"],"infoHash":"80d0e1336f6d21585c45868434f923debc0c8e47","infoHashBuffer":{"type":"Buffer","data":[128,208,225,51,111,109,33,88,92,69,134,132,52,249,35,222,188,12,142,71]},"announce":[],"urlList":[]}}