{"title":"Urban.Freestyler.S03E17.PDTV.x264-WaLMaRT","uid":13741499,"size":40306946,"categoryP":"video","categoryS":"tv_shows","magnet":"?xt=urn:btih:81933187442a1ee31ace8a51484d09a2b97d9823&amp;dn=Urban.Freestyler.S03E17.PDTV.x264-WaLMaRT&amp;tr=udp%3A%2F%2Ftracker.leechers-paradise.org%3A6969&amp;tr=udp%3A%2F%2Fzer0day.ch%3A1337&amp;tr=udp%3A%2F%2Fopen.demonii.com%3A1337&amp;tr=udp%3A%2F%2Ftracker.coppersurfer.tk%3A6969&amp;tr=udp%3A%2F%2Fexodus.desync.com%3A6969","seeders":0,"leechers":0,"uploader":"TvTeam","files":5,"time":1457083006,"description":"https://www.torrenting.com\r\n\r\nSign up is OPEN - for time being. Come and have fun.\r\n\r\n------------------------------------------------------------------------\r\n\r\nReNEW our seedbox by donating bitcoin To: 1N1qWp6Hk1REFXgJ8yviqCnLsn76BfXFh1","torrent":{"xt":"urn:btih:81933187442a1ee31ace8a51484d09a2b97d9823","amp;dn":"Urban.Freestyler.S03E17.PDTV.x264-WaLMaRT","amp;tr":["udp%3A%2F%2Ftracker.leechers-paradise.org%3A6969","udp%3A%2F%2Fzer0day.ch%3A1337","udp%3A%2F%2Fopen.demonii.com%3A1337","udp%3A%2F%2Ftracker.coppersurfer.tk%3A6969","udp%3A%2F%2Fexodus.desync.com%3A6969"],"infoHash":"81933187442a1ee31ace8a51484d09a2b97d9823","infoHashBuffer":{"type":"Buffer","data":[129,147,49,135,68,42,30,227,26,206,138,81,72,77,9,162,185,125,152,35]},"announce":[],"urlList":[]}}