{"title":"SakimiChan Patreon term 8","uid":13671756,"size":5985298720,"categoryP":"video","categoryS":"other","magnet":"?xt=urn:btih:8e149079d97f6b51a9aebc5572df37a150bb17e7&amp;dn=SakimiChan+Patreon+term+8&amp;tr=udp%3A%2F%2Ftracker.leechers-paradise.org%3A6969&amp;tr=udp%3A%2F%2Fzer0day.ch%3A1337&amp;tr=udp%3A%2F%2Fopen.demonii.com%3A1337&amp;tr=udp%3A%2F%2Ftracker.coppersurfer.tk%3A6969&amp;tr=udp%3A%2F%2Fexodus.desync.com%3A6969","seeders":0,"leechers":3,"uploader":"walterrenan","files":33,"time":1456347934,"description":"pack vídeos of artist sakimichan with vídeo overvoice tutorial and vídeo process full \r\n3~6hrs per vídeo.\r\n\r\nscreeshot: \nhttp://i.imgur.com/ddoj7vP.png\r\n \nhttp://i.imgur.com/J2w6qIM.png","torrent":{"xt":"urn:btih:8e149079d97f6b51a9aebc5572df37a150bb17e7","amp;dn":"SakimiChan+Patreon+term+8","amp;tr":["udp%3A%2F%2Ftracker.leechers-paradise.org%3A6969","udp%3A%2F%2Fzer0day.ch%3A1337","udp%3A%2F%2Fopen.demonii.com%3A1337","udp%3A%2F%2Ftracker.coppersurfer.tk%3A6969","udp%3A%2F%2Fexodus.desync.com%3A6969"],"infoHash":"8e149079d97f6b51a9aebc5572df37a150bb17e7","infoHashBuffer":{"type":"Buffer","data":[142,20,144,121,217,127,107,81,169,174,188,85,114,223,55,161,80,187,23,231]},"announce":[],"urlList":[]}}