{"title":"A Birthday To Remember! -Naomi Woods - (Bangbros - BangPOV) - NE","uid":13847485,"size":212090198,"categoryP":"porn","categoryS":"movie_clips","magnet":"?xt=urn:btih:8e873df22d9f307e57be1f78760a6d32407eabe7&amp;dn=A+Birthday+To+Remember%21+-Naomi+Woods+-+%28Bangbros+-+BangPOV%29+-+NE&amp;tr=udp%3A%2F%2Ftracker.leechers-paradise.org%3A6969&amp;tr=udp%3A%2F%2Fzer0day.ch%3A1337&amp;tr=udp%3A%2F%2Fopen.demonii.com%3A1337&amp;tr=udp%3A%2F%2Ftracker.coppersurfer.tk%3A6969&amp;tr=udp%3A%2F%2Fexodus.desync.com%3A6969","seeders":0,"leechers":0,"uploader":"Piratepr0n","files":1,"time":1457879599,"description":"-------------------------------------------------------------------------------------\nName:\nA Birthday To Remember! -Naomi Woods - (Bangbros - BangPOV) - NEW March 13, 2016 torrent NEW.avi\n-------------------------------------------------------------------------------------\nFile list:\nA Birthday To Remember! -Naomi Woods - (Bangbros - BangPOV) - NEW March 13, 2016 torrent NEW.avi (202 MiB | 640x360 | 24min 33s | AVI) \nhttp://imgfapper.com/img-56e56c182dcc1.html","torrent":{"xt":"urn:btih:8e873df22d9f307e57be1f78760a6d32407eabe7","amp;dn":"A+Birthday+To+Remember%21+-Naomi+Woods+-+%28Bangbros+-+BangPOV%29+-+NE","amp;tr":["udp%3A%2F%2Ftracker.leechers-paradise.org%3A6969","udp%3A%2F%2Fzer0day.ch%3A1337","udp%3A%2F%2Fopen.demonii.com%3A1337","udp%3A%2F%2Ftracker.coppersurfer.tk%3A6969","udp%3A%2F%2Fexodus.desync.com%3A6969"],"infoHash":"8e873df22d9f307e57be1f78760a6d32407eabe7","infoHashBuffer":{"type":"Buffer","data":[142,135,61,242,45,159,48,126,87,190,31,120,118,10,109,50,64,126,171,231]},"announce":[],"urlList":[]}}