{"title":"[FakeAgent] Anastasia - Stunning blonde loves taking cock E478","uid":13617486,"size":768315854,"categoryP":"porn","categoryS":"movie_clips","magnet":"?xt=urn:btih:9366f5cf0a2e06bbf3bde79e727ccb5329616de7&amp;dn=%5BFakeAgent%5D+Anastasia+-+Stunning+blonde+loves+taking+cock+E478&amp;tr=udp%3A%2F%2Ftracker.leechers-paradise.org%3A6969&amp;tr=udp%3A%2F%2Fzer0day.ch%3A1337&amp;tr=udp%3A%2F%2Fopen.demonii.com%3A1337&amp;tr=udp%3A%2F%2Ftracker.coppersurfer.tk%3A6969&amp;tr=udp%3A%2F%2Fexodus.desync.com%3A6969","seeders":0,"leechers":1,"uploader":"C47wh15p3r3r","files":1,"time":1455955089,"description":"[FakeAgent] Anastasia - Stunning blonde loves taking cock E478\r\n\r\nScreenshots: \nhttp://imgarte.com/?v=737218 \nhttp://imgarte.com/?v=306549","torrent":{"xt":"urn:btih:9366f5cf0a2e06bbf3bde79e727ccb5329616de7","amp;dn":"%5BFakeAgent%5D+Anastasia+-+Stunning+blonde+loves+taking+cock+E478","amp;tr":["udp%3A%2F%2Ftracker.leechers-paradise.org%3A6969","udp%3A%2F%2Fzer0day.ch%3A1337","udp%3A%2F%2Fopen.demonii.com%3A1337","udp%3A%2F%2Ftracker.coppersurfer.tk%3A6969","udp%3A%2F%2Fexodus.desync.com%3A6969"],"infoHash":"9366f5cf0a2e06bbf3bde79e727ccb5329616de7","infoHashBuffer":{"type":"Buffer","data":[147,102,245,207,10,46,6,187,243,189,231,158,114,124,203,83,41,97,109,231]},"announce":[],"urlList":[]}}