{"title":"Ancient History Book Collection and Audiobooks","uid":13756713,"size":7343068553,"categoryP":"other","categoryS":"e_books","magnet":"?xt=urn:btih:97089fbc38b823102cd91bcc0ad02a839b43aa8c&amp;dn=Ancient+History+Book+Collection+and+Audiobooks&amp;tr=udp%3A%2F%2Ftracker.leechers-paradise.org%3A6969&amp;tr=udp%3A%2F%2Fzer0day.ch%3A1337&amp;tr=udp%3A%2F%2Fopen.demonii.com%3A1337&amp;tr=udp%3A%2F%2Ftracker.coppersurfer.tk%3A6969&amp;tr=udp%3A%2F%2Fexodus.desync.com%3A6969","seeders":0,"leechers":1,"uploader":"Kane_krit","files":1423,"time":1457201211,"description":"Book collections and audio book on the ancient world.\r\n\r\n\r\nAlexander the Great and the Hellenistic Age (Audio)\r\n\r\nAncient Greek Civilization (Audio)\r\n\r\nBetween the Rivers; The History of Ancient Mesopotamia (Audio)\r\n\r\nCities and Societies of Ancient Troy\r\n\r\nDiscovery of Ancient Civilizations (Audio)\r\n\r\nGreat Ancient Civilizations of Asia Minor (Audio)\r\n\r\nGreat Pharaohs of Ancient Egypt (Audio)\r\n\r\nGreek and Persian Wars (Audio)\r\n\r\nHebrews, Greeks, and Romans - The Foundations of Western Civilization (Audio)\r\n\r\nHistory of Ancient Egypt (Audio)\r\n\r\nHistory Of Ancient Sparta\r\n\r\nHuman Prehistory and the First Civilizations (Audio)\r\n\r\nLong Shadow of the Ancient Greek World (Audio)\r\n\r\nNeolithic Europe\r\n\r\nOrigin of Civilization (Audio)\r\n\r\nPersian Fire - The First World Empire and the Battle for the West\r\n\r\nRise and Fall of Alexandria - Birthplace of the Modern Mind (Audio)\r\n\r\nThe Cambridge Ancient History\r\n\r\nThe Cambridge History of Hellenistic Philosophy\r\n\r\nThe Cambridge History of Later Greek and Early Medieval Philosophy\r\n\r\nttc - History of the Ancient World, A Global Perspective","torrent":{"xt":"urn:btih:97089fbc38b823102cd91bcc0ad02a839b43aa8c","amp;dn":"Ancient+History+Book+Collection+and+Audiobooks","amp;tr":["udp%3A%2F%2Ftracker.leechers-paradise.org%3A6969","udp%3A%2F%2Fzer0day.ch%3A1337","udp%3A%2F%2Fopen.demonii.com%3A1337","udp%3A%2F%2Ftracker.coppersurfer.tk%3A6969","udp%3A%2F%2Fexodus.desync.com%3A6969"],"infoHash":"97089fbc38b823102cd91bcc0ad02a839b43aa8c","infoHashBuffer":{"type":"Buffer","data":[151,8,159,188,56,184,35,16,44,217,27,204,10,208,42,131,155,67,170,140]},"announce":[],"urlList":[]}}