{"title":"batman begins ps2","uid":13644559,"size":1636930347,"categoryP":"games","categoryS":"psx","magnet":"?xt=urn:btih:9b04d9e5a8ce65c669b4fc348193aefd842b76af&amp;dn=batman+begins+ps2&amp;tr=udp%3A%2F%2Ftracker.leechers-paradise.org%3A6969&amp;tr=udp%3A%2F%2Fzer0day.ch%3A1337&amp;tr=udp%3A%2F%2Fopen.demonii.com%3A1337&amp;tr=udp%3A%2F%2Ftracker.coppersurfer.tk%3A6969&amp;tr=udp%3A%2F%2Fexodus.desync.com%3A6969","seeders":0,"leechers":1,"uploader":"alef55","files":2,"time":1456154266,"description":"Título do Game: Batman: Begins\r\nGênero: Ação, Aventura\r\nPlataforma: PS2\r\nTamanho: 1.6 GB","torrent":{"xt":"urn:btih:9b04d9e5a8ce65c669b4fc348193aefd842b76af","amp;dn":"batman+begins+ps2","amp;tr":["udp%3A%2F%2Ftracker.leechers-paradise.org%3A6969","udp%3A%2F%2Fzer0day.ch%3A1337","udp%3A%2F%2Fopen.demonii.com%3A1337","udp%3A%2F%2Ftracker.coppersurfer.tk%3A6969","udp%3A%2F%2Fexodus.desync.com%3A6969"],"infoHash":"9b04d9e5a8ce65c669b4fc348193aefd842b76af","infoHashBuffer":{"type":"Buffer","data":[155,4,217,229,168,206,101,198,105,180,252,52,129,147,174,253,132,43,118,175]},"announce":[],"urlList":[]}}