{"title":"MommyGotBoobs Mercedes Carrera Mommy Method XXX 1080p 16.03.16","uid":13887220,"size":2621500725,"categoryP":"porn","categoryS":"hd___movies","magnet":"?xt=urn:btih:a1824618dbbd7e96344884b9936286106e9b5dc9&amp;dn=MommyGotBoobs+Mercedes+Carrera+Mommy+Method+XXX+1080p+16.03.16&amp;tr=udp%3A%2F%2Ftracker.leechers-paradise.org%3A6969&amp;tr=udp%3A%2F%2Fzer0day.ch%3A1337&amp;tr=udp%3A%2F%2Fopen.demonii.com%3A1337&amp;tr=udp%3A%2F%2Ftracker.coppersurfer.tk%3A6969&amp;tr=udp%3A%2F%2Fexodus.desync.com%3A6969","seeders":0,"leechers":4,"uploader":"thfatboys","files":1,"time":1458182444,"description":"Screens: \nhttp://imgpeak.com/img-56e9cb75dc2dd.html","torrent":{"xt":"urn:btih:a1824618dbbd7e96344884b9936286106e9b5dc9","amp;dn":"MommyGotBoobs+Mercedes+Carrera+Mommy+Method+XXX+1080p+16.03.16","amp;tr":["udp%3A%2F%2Ftracker.leechers-paradise.org%3A6969","udp%3A%2F%2Fzer0day.ch%3A1337","udp%3A%2F%2Fopen.demonii.com%3A1337","udp%3A%2F%2Ftracker.coppersurfer.tk%3A6969","udp%3A%2F%2Fexodus.desync.com%3A6969"],"infoHash":"a1824618dbbd7e96344884b9936286106e9b5dc9","infoHashBuffer":{"type":"Buffer","data":[161,130,70,24,219,189,126,150,52,72,132,185,147,98,134,16,110,155,93,201]},"announce":[],"urlList":[]}}