{"title":"BigTitsAtSchool - Parker Swayze - Expose Yourself To Higher Lear","uid":13769400,"size":274329694,"categoryP":"porn","categoryS":"movie_clips","magnet":"?xt=urn:btih:a1cd91b8b465cab1450190272e9f90cc9a925c92&amp;dn=BigTitsAtSchool+-+Parker+Swayze+-+Expose+Yourself+To+Higher+Lear&amp;tr=udp%3A%2F%2Ftracker.leechers-paradise.org%3A6969&amp;tr=udp%3A%2F%2Fzer0day.ch%3A1337&amp;tr=udp%3A%2F%2Fopen.demonii.com%3A1337&amp;tr=udp%3A%2F%2Ftracker.coppersurfer.tk%3A6969&amp;tr=udp%3A%2F%2Fexodus.desync.com%3A6969","seeders":0,"leechers":1,"uploader":"ImgSnaps","files":1,"time":1457282067,"description":"Screenshots :\r\n \nhttp://imgsnaps.com/image/y2w\r\n \nhttp://imgsnaps.com/image/y2r","torrent":{"xt":"urn:btih:a1cd91b8b465cab1450190272e9f90cc9a925c92","amp;dn":"BigTitsAtSchool+-+Parker+Swayze+-+Expose+Yourself+To+Higher+Lear","amp;tr":["udp%3A%2F%2Ftracker.leechers-paradise.org%3A6969","udp%3A%2F%2Fzer0day.ch%3A1337","udp%3A%2F%2Fopen.demonii.com%3A1337","udp%3A%2F%2Ftracker.coppersurfer.tk%3A6969","udp%3A%2F%2Fexodus.desync.com%3A6969"],"infoHash":"a1cd91b8b465cab1450190272e9f90cc9a925c92","infoHashBuffer":{"type":"Buffer","data":[161,205,145,184,180,101,202,177,69,1,144,39,46,159,144,204,154,146,92,146]},"announce":[],"urlList":[]}}