{"title":"KENNY_BEGINS.ISO","uid":13606187,"size":4681517056,"categoryP":"video","categoryS":"movies_dvdr","magnet":"?xt=urn:btih:a54d8e9d7d14956612d04577bba2df46bea47d42&amp;dn=KENNY_BEGINS.ISO&amp;tr=udp%3A%2F%2Ftracker.leechers-paradise.org%3A6969&amp;tr=udp%3A%2F%2Fzer0day.ch%3A1337&amp;tr=udp%3A%2F%2Fopen.demonii.com%3A1337&amp;tr=udp%3A%2F%2Ftracker.coppersurfer.tk%3A6969&amp;tr=udp%3A%2F%2Fexodus.desync.com%3A6969","seeders":0,"leechers":0,"uploader":"torggatan11","files":1,"time":1455886995,"description":"KENNY_BEGINS.ISO the movie + 45 minutes extras \r\n\r\nenyoy \r\n\r\nreuest movie\r\n\r\n2008\r\n\r\ngenre humor with johan rheborg bill skarsgård\r\n\r\nand other peoples","torrent":{"xt":"urn:btih:a54d8e9d7d14956612d04577bba2df46bea47d42","amp;dn":"KENNY_BEGINS.ISO","amp;tr":["udp%3A%2F%2Ftracker.leechers-paradise.org%3A6969","udp%3A%2F%2Fzer0day.ch%3A1337","udp%3A%2F%2Fopen.demonii.com%3A1337","udp%3A%2F%2Ftracker.coppersurfer.tk%3A6969","udp%3A%2F%2Fexodus.desync.com%3A6969"],"infoHash":"a54d8e9d7d14956612d04577bba2df46bea47d42","infoHashBuffer":{"type":"Buffer","data":[165,77,142,157,125,20,149,102,18,208,69,119,187,162,223,70,190,164,125,66]},"announce":[],"urlList":[]}}