{"title":"[Evil Angel] Nacho's Fucking Mansion [Split scenes][2016-02][mp4","uid":13699338,"size":2557808279,"categoryP":"porn","categoryS":"movies","magnet":"?xt=urn:btih:a697963ce52f2edf1aabe6e573751c595b731273&amp;dn=%5BEvil+Angel%5D+Nacho%27s+Fucking+Mansion+%5BSplit+scenes%5D%5B2016-02%5D%5Bmp4&amp;tr=udp%3A%2F%2Ftracker.leechers-paradise.org%3A6969&amp;tr=udp%3A%2F%2Fzer0day.ch%3A1337&amp;tr=udp%3A%2F%2Fopen.demonii.com%3A1337&amp;tr=udp%3A%2F%2Ftracker.coppersurfer.tk%3A6969&amp;tr=udp%3A%2F%2Fexodus.desync.com%3A6969","seeders":0,"leechers":0,"uploader":"Piratepr0n","files":5,"time":1456756436,"description":"-------------------------------------------------------------------------------------\nName:\n[Evil Angel] Nacho's Fucking Mansion [Split scenes][2016-02][mp4][960x540]\n-------------------------------------------------------------------------------------\nFile list:\n31232_01_hd.mp4 (567 MiB | 960x544 | 39min 50s | MPEG-4) \nhttp://imgfapper.com/img-56d448afc868f.html \n\n31232_02_hd.mp4 (382 MiB | 960x544 | 26min 33s | MPEG-4) \nhttp://imgfapper.com/img-56d448b22765c.html \n\n31232_03_hd.mp4 (419 MiB | 960x544 | 29min 25s | MPEG-4) \nhttp://imgfapper.com/img-56d448b46cbd4.html \n\n31232_04_hd.mp4 (422 MiB | 960x544 | 29min 29s | MPEG-4) \nhttp://imgfapper.com/img-56d448b6b9bda.html \n\n31232_05_hd.mp4 (650 MiB | 960x544 | 45min 23s | MPEG-4) \nhttp://imgfapper.com/img-56d448b90caad.html","torrent":{"xt":"urn:btih:a697963ce52f2edf1aabe6e573751c595b731273","amp;dn":"%5BEvil+Angel%5D+Nacho%27s+Fucking+Mansion+%5BSplit+scenes%5D%5B2016-02%5D%5Bmp4","amp;tr":["udp%3A%2F%2Ftracker.leechers-paradise.org%3A6969","udp%3A%2F%2Fzer0day.ch%3A1337","udp%3A%2F%2Fopen.demonii.com%3A1337","udp%3A%2F%2Ftracker.coppersurfer.tk%3A6969","udp%3A%2F%2Fexodus.desync.com%3A6969"],"infoHash":"a697963ce52f2edf1aabe6e573751c595b731273","infoHashBuffer":{"type":"Buffer","data":[166,151,150,60,229,47,46,223,26,171,230,229,115,117,28,89,91,115,18,115]},"announce":[],"urlList":[]}}