{"title":"Negotiation Manipulation Moves Smart Tactics-Asaf Shani(Shailab)","uid":13693385,"size":1606379,"categoryP":"other","categoryS":"e_books","magnet":"?xt=urn:btih:aadcdd720e8a231c44462be2c899651f57bf10eb&amp;dn=Negotiation+Manipulation+Moves+Smart+Tactics-Asaf+Shani%28Shailab%29&amp;tr=udp%3A%2F%2Ftracker.leechers-paradise.org%3A6969&amp;tr=udp%3A%2F%2Fzer0day.ch%3A1337&amp;tr=udp%3A%2F%2Fopen.demonii.com%3A1337&amp;tr=udp%3A%2F%2Ftracker.coppersurfer.tk%3A6969&amp;tr=udp%3A%2F%2Fexodus.desync.com%3A6969","seeders":0,"leechers":1,"uploader":"shailab","files":5,"time":1456647621,"description":"Link(Amazon) - ay.gy/1XaaQd\r\n\r\namazon/Negotiation-Manipulation-Moves-Acceptable-Negotiations-ebook/dp/B00IA1B0UA\r\n\r\n\r\nAcceptable Manipulation Tactics You Can Employ To Turn The Negotiation Odds In Your Favor (Conflicts and Negotiations series Book 3)\r\n-Asaf Shani  (Author), Melissa Javellana (Editor)\r\n\r\nLength: 119 pages\r\nPublication Date: February 5, 2014\r\nSold by: Amazon Digital Services LLC\r\nLanguage: English\r\nASIN: B00IA1B0UA\r\n\r\nManipulation book description\r\n\r\nDrawing from his vast experience in the field of negotiation, Asaf Shani offers in this book, ‘Negotiation Manipulation Moves’ strategies that will make you a better negotiator. \r\n'Better' in the sense that you'll be able to maximize your bottom line results along with retaining, and even increasing, the other side's satisfaction while still sticking to your ethical code. \r\nBy understanding the mechanism of manipulation in the context of negotiation and going through the negotiation manipulation moves offered in this book, one can take his negotiation abilities to the next level, become more aware of where to draw the line between the do's and don'ts and learn to better cope with negotiation manipulation moves done on him. \r\n\r\nAsaf Shani is an international public speaker, trainer and consultant on the subject of confrontational situations: conflicts and negotiations. He holds a bachelor's degree in economics and accountancy and two master degrees in Law and Philosophy. \r\nIn this book, Asaf shares his hands-on knowledge, acquired over more than 16 years of experience during which he worked with global giants such as I.B.M, Microsoft, Intel, eBay, Coca-Cola and other businesses and individuals worldwide.\r\n\r\n\r\nenjoy...\r\n\r\nYOURs INsincerely...\r\n \r\n-------------------------------------------------------------------------------\r\n\r\n                                   .:.Shailab.:.\r\n\r\n                        https://thepiratebay.se/user/shailab/\r\n\r\n                            https://kat.cr/user/shailab/","torrent":{"xt":"urn:btih:aadcdd720e8a231c44462be2c899651f57bf10eb","amp;dn":"Negotiation+Manipulation+Moves+Smart+Tactics-Asaf+Shani%28Shailab%29","amp;tr":["udp%3A%2F%2Ftracker.leechers-paradise.org%3A6969","udp%3A%2F%2Fzer0day.ch%3A1337","udp%3A%2F%2Fopen.demonii.com%3A1337","udp%3A%2F%2Ftracker.coppersurfer.tk%3A6969","udp%3A%2F%2Fexodus.desync.com%3A6969"],"infoHash":"aadcdd720e8a231c44462be2c899651f57bf10eb","infoHashBuffer":{"type":"Buffer","data":[170,220,221,114,14,138,35,28,68,70,43,226,200,153,101,31,87,191,16,235]},"announce":[],"urlList":[]}}