{"title":"1By-Day 16 03 28 Blanche Bradburry XXX 1080p MP4-KTR","uid":14068840,"size":1455570101,"categoryP":"porn","categoryS":"hd___movies","magnet":"?xt=urn:btih:acfa0817d6be0b5881702a2234932c5b89eafedb&amp;dn=1By-Day+16+03+28+Blanche+Bradburry+XXX+1080p+MP4-KTR&amp;tr=udp%3A%2F%2Ftracker.leechers-paradise.org%3A6969&amp;tr=udp%3A%2F%2Fzer0day.ch%3A1337&amp;tr=udp%3A%2F%2Fopen.demonii.com%3A1337&amp;tr=udp%3A%2F%2Ftracker.coppersurfer.tk%3A6969&amp;tr=udp%3A%2F%2Fexodus.desync.com%3A6969","seeders":0,"leechers":0,"uploader":"0-DayXXX","files":1,"time":1459146549,"description":"------------------------------------------------\n1By-Day.16.03.28.Blanche.Bradburry.XXX.1080p.MP4-KTR\n------------------------------------------------\nScreenshot(s): \nhttp://imgsay.com/?v=865695 \n\n------------------------------------------------\nInfo(s):\nFormat:\t\tMPEG-4\nSize:\t\t1.36 GiB\nDuration:\t23min 41s\nResolution:\t1920x1080\nBitrate:\tVariable\n------------------------------------------------\n         ** More 0-DayXXX Uploads ** \nhttp://youpornbook.com\n------------------------------------------------\nIf you like this torrent, please post a comment!\n            Don't forget to seed!","torrent":{"xt":"urn:btih:acfa0817d6be0b5881702a2234932c5b89eafedb","amp;dn":"1By-Day+16+03+28+Blanche+Bradburry+XXX+1080p+MP4-KTR","amp;tr":["udp%3A%2F%2Ftracker.leechers-paradise.org%3A6969","udp%3A%2F%2Fzer0day.ch%3A1337","udp%3A%2F%2Fopen.demonii.com%3A1337","udp%3A%2F%2Ftracker.coppersurfer.tk%3A6969","udp%3A%2F%2Fexodus.desync.com%3A6969"],"infoHash":"acfa0817d6be0b5881702a2234932c5b89eafedb","infoHashBuffer":{"type":"Buffer","data":[172,250,8,23,214,190,11,88,129,112,42,34,52,147,44,91,137,234,254,219]},"announce":[],"urlList":[]}}