{"title":"Long.Lost.Family.AU.S01E01.XviD-AFG","uid":13997679,"size":542016056,"categoryP":"video","categoryS":"tv_shows","magnet":"?xt=urn:btih:b10bae96d00c7aa9461baa7dfc85982542a52f27&amp;dn=Long.Lost.Family.AU.S01E01.XviD-AFG&amp;tr=udp%3A%2F%2Ftracker.leechers-paradise.org%3A6969&amp;tr=udp%3A%2F%2Fzer0day.ch%3A1337&amp;tr=udp%3A%2F%2Fopen.demonii.com%3A1337&amp;tr=udp%3A%2F%2Ftracker.coppersurfer.tk%3A6969&amp;tr=udp%3A%2F%2Fexodus.desync.com%3A6969","seeders":0,"leechers":1,"uploader":"TvTeam","files":12,"time":1458756073,"description":"https://www.torrenting.com\r\n\r\nSign up is OPEN - for time being. Come and have fun.\r\n\r\n------------------------------------------------------------------------\r\n\r\nReNEW our seedbox by donating bitcoin To: 1N1qWp6Hk1REFXgJ8yviqCnLsn76BfXFh1","torrent":{"xt":"urn:btih:b10bae96d00c7aa9461baa7dfc85982542a52f27","amp;dn":"Long.Lost.Family.AU.S01E01.XviD-AFG","amp;tr":["udp%3A%2F%2Ftracker.leechers-paradise.org%3A6969","udp%3A%2F%2Fzer0day.ch%3A1337","udp%3A%2F%2Fopen.demonii.com%3A1337","udp%3A%2F%2Ftracker.coppersurfer.tk%3A6969","udp%3A%2F%2Fexodus.desync.com%3A6969"],"infoHash":"b10bae96d00c7aa9461baa7dfc85982542a52f27","infoHashBuffer":{"type":"Buffer","data":[177,11,174,150,208,12,122,169,70,27,170,125,252,133,152,37,66,165,47,39]},"announce":[],"urlList":[]}}