{"title":"Military Modelcraft International - April 2016","uid":14012921,"size":28474497,"categoryP":"other","categoryS":"e_books","magnet":"?xt=urn:btih:b1b94b831fc26a62786d02ceec8013de096a9835&amp;dn=Military+Modelcraft+International+-+April+2016&amp;tr=udp%3A%2F%2Ftracker.leechers-paradise.org%3A6969&amp;tr=udp%3A%2F%2Fzer0day.ch%3A1337&amp;tr=udp%3A%2F%2Fopen.demonii.com%3A1337&amp;tr=udp%3A%2F%2Ftracker.coppersurfer.tk%3A6969&amp;tr=udp%3A%2F%2Fexodus.desync.com%3A6969","seeders":0,"leechers":1,"uploader":"Orangie2Dope","files":1,"time":1458843364,"description":"English | 78 pages | PDF | 27.2 MB\r\n\r\nThe No.1 Model Military Magazine","torrent":{"xt":"urn:btih:b1b94b831fc26a62786d02ceec8013de096a9835","amp;dn":"Military+Modelcraft+International+-+April+2016","amp;tr":["udp%3A%2F%2Ftracker.leechers-paradise.org%3A6969","udp%3A%2F%2Fzer0day.ch%3A1337","udp%3A%2F%2Fopen.demonii.com%3A1337","udp%3A%2F%2Ftracker.coppersurfer.tk%3A6969","udp%3A%2F%2Fexodus.desync.com%3A6969"],"infoHash":"b1b94b831fc26a62786d02ceec8013de096a9835","infoHashBuffer":{"type":"Buffer","data":[177,185,75,131,31,194,106,98,120,109,2,206,236,128,19,222,9,106,152,53]},"announce":[],"urlList":[]}}