{"title":"Real prozzie gets cumshot","uid":14106185,"size":106992312,"categoryP":"porn","categoryS":"movie_clips","magnet":"?xt=urn:btih:b2195a8f0d0e3616deb09191236c32bc797ecf2c&amp;dn=Real+prozzie+gets+cumshot&amp;tr=udp%3A%2F%2Ftracker.leechers-paradise.org%3A6969&amp;tr=udp%3A%2F%2Fzer0day.ch%3A1337&amp;tr=udp%3A%2F%2Fopen.demonii.com%3A1337&amp;tr=udp%3A%2F%2Ftracker.coppersurfer.tk%3A6969&amp;tr=udp%3A%2F%2Fexodus.desync.com%3A6969","seeders":0,"leechers":0,"uploader":"demonoidt","files":1,"time":1459357097,"description":"Samples\r\n \nhttp://demonoid.co/2016/03/30/real-prozzie-gets-cumshot/\r\n \nhttp://adultwallpapers.co.in/real-prozzie-gets-cumshot/","torrent":{"xt":"urn:btih:b2195a8f0d0e3616deb09191236c32bc797ecf2c","amp;dn":"Real+prozzie+gets+cumshot","amp;tr":["udp%3A%2F%2Ftracker.leechers-paradise.org%3A6969","udp%3A%2F%2Fzer0day.ch%3A1337","udp%3A%2F%2Fopen.demonii.com%3A1337","udp%3A%2F%2Ftracker.coppersurfer.tk%3A6969","udp%3A%2F%2Fexodus.desync.com%3A6969"],"infoHash":"b2195a8f0d0e3616deb09191236c32bc797ecf2c","infoHashBuffer":{"type":"Buffer","data":[178,25,90,143,13,14,54,22,222,176,145,145,35,108,50,188,121,126,207,44]},"announce":[],"urlList":[]}}