{"title":"Woman - March 28, 2016","uid":13980171,"size":28246995,"categoryP":"other","categoryS":"e_books","magnet":"?xt=urn:btih:b6d9f83a1cf20f6e4a320aa4f5406979ac2aa5b0&amp;dn=Woman+-+March+28%2C+2016&amp;tr=udp%3A%2F%2Ftracker.leechers-paradise.org%3A6969&amp;tr=udp%3A%2F%2Fzer0day.ch%3A1337&amp;tr=udp%3A%2F%2Fopen.demonii.com%3A1337&amp;tr=udp%3A%2F%2Ftracker.coppersurfer.tk%3A6969&amp;tr=udp%3A%2F%2Fexodus.desync.com%3A6969","seeders":0,"leechers":0,"uploader":"Orangie2Dope","files":1,"time":1458682915,"description":"English | 72 pages | PDF | 26.9 MB\r\n\r\n\r\n\r\n\r\n\r\nWoman UK is a must-have weekly fix of hot celebrity news, juicy TV insider gossip, compelling real life stories and body confident fashion and beauty. Its lifestyle section offers brilliant ideas on homes and interiors, the latest product news and user-friendly advice. Woman is first for food too with healthy family friendly menu ideas","torrent":{"xt":"urn:btih:b6d9f83a1cf20f6e4a320aa4f5406979ac2aa5b0","amp;dn":"Woman+-+March+28%2C+2016","amp;tr":["udp%3A%2F%2Ftracker.leechers-paradise.org%3A6969","udp%3A%2F%2Fzer0day.ch%3A1337","udp%3A%2F%2Fopen.demonii.com%3A1337","udp%3A%2F%2Ftracker.coppersurfer.tk%3A6969","udp%3A%2F%2Fexodus.desync.com%3A6969"],"infoHash":"b6d9f83a1cf20f6e4a320aa4f5406979ac2aa5b0","infoHashBuffer":{"type":"Buffer","data":[182,217,248,58,28,242,15,110,74,50,10,164,245,64,105,121,172,42,165,176]},"announce":[],"urlList":[]}}