{"title":"MyNaughtyAlbum.16.03.07.Morgan.Rodriguez.XXX.1080p.MP4-KTR[VR56]","uid":13800053,"size":2313486521,"categoryP":"porn","categoryS":"movie_clips","magnet":"?xt=urn:btih:b962be7b5b1ead6ec6cd940a9aa613f90b331a49&amp;dn=MyNaughtyAlbum.16.03.07.Morgan.Rodriguez.XXX.1080p.MP4-KTR%5BVR56%5D&amp;tr=udp%3A%2F%2Ftracker.leechers-paradise.org%3A6969&amp;tr=udp%3A%2F%2Fzer0day.ch%3A1337&amp;tr=udp%3A%2F%2Fopen.demonii.com%3A1337&amp;tr=udp%3A%2F%2Ftracker.coppersurfer.tk%3A6969&amp;tr=udp%3A%2F%2Fexodus.desync.com%3A6969","seeders":0,"leechers":0,"uploader":"Piratepr0n","files":1,"time":1457447018,"description":"-------------------------------------------------------------------------------------\nName:\nMyNaughtyAlbum.16.03.07.Morgan.Rodriguez.XXX.1080p.MP4-KTR[VR56]\n-------------------------------------------------------------------------------------\nFile list:\npdmmna.16.03.07.morgan.rodriguez[VR56].mp4 (2.15 GiB | 1920x1080 | 25min 24s | MPEG-4) \nhttp://imgfapper.com/img-56ded25120be1.html","torrent":{"xt":"urn:btih:b962be7b5b1ead6ec6cd940a9aa613f90b331a49","amp;dn":"MyNaughtyAlbum.16.03.07.Morgan.Rodriguez.XXX.1080p.MP4-KTR%5BVR56%5D","amp;tr":["udp%3A%2F%2Ftracker.leechers-paradise.org%3A6969","udp%3A%2F%2Fzer0day.ch%3A1337","udp%3A%2F%2Fopen.demonii.com%3A1337","udp%3A%2F%2Ftracker.coppersurfer.tk%3A6969","udp%3A%2F%2Fexodus.desync.com%3A6969"],"infoHash":"b962be7b5b1ead6ec6cd940a9aa613f90b331a49","infoHashBuffer":{"type":"Buffer","data":[185,98,190,123,91,30,173,110,198,205,148,10,154,166,19,249,11,51,26,73]},"announce":[],"urlList":[]}}