{"title":"FakeAgent - Hot Amateur wants to be a model - Aruna Aghora.mp4","uid":13690353,"size":797161223,"categoryP":"porn","categoryS":"movie_clips","magnet":"?xt=urn:btih:c5937df26c2462b4a355b9702fd3b5350b53cf1b&amp;dn=FakeAgent+-+Hot+Amateur+wants+to+be+a+model+-+Aruna+Aghora.mp4&amp;tr=udp%3A%2F%2Ftracker.leechers-paradise.org%3A6969&amp;tr=udp%3A%2F%2Fzer0day.ch%3A1337&amp;tr=udp%3A%2F%2Fopen.demonii.com%3A1337&amp;tr=udp%3A%2F%2Ftracker.coppersurfer.tk%3A6969&amp;tr=udp%3A%2F%2Fexodus.desync.com%3A6969","seeders":0,"leechers":1,"uploader":"Pr0nmaster","files":1,"time":1456610937,"description":"FakeAgent - Hot Amateur wants to be a model - Aruna Aghora.mp4\r\n\r\n2016, Amateur, Casting, POV, All Sex, Oral, Hardcore, XXX, Adult\r\n\r\n760.23 MB\r\n\r\nScreens\r\n \nhttp://imgcentral.com/viewer.php?file=61506289564179287592.jpg\r\n \nhttp://imgcentral.com/viewer.php?file=98112987388428225280.jpg\r\n \nhttp://imgcentral.com/viewer.php?file=63491358686603329811.jpg\r\n \nhttp://imgcentral.com/viewer.php?file=97472584955896696815.jpg","torrent":{"xt":"urn:btih:c5937df26c2462b4a355b9702fd3b5350b53cf1b","amp;dn":"FakeAgent+-+Hot+Amateur+wants+to+be+a+model+-+Aruna+Aghora.mp4","amp;tr":["udp%3A%2F%2Ftracker.leechers-paradise.org%3A6969","udp%3A%2F%2Fzer0day.ch%3A1337","udp%3A%2F%2Fopen.demonii.com%3A1337","udp%3A%2F%2Ftracker.coppersurfer.tk%3A6969","udp%3A%2F%2Fexodus.desync.com%3A6969"],"infoHash":"c5937df26c2462b4a355b9702fd3b5350b53cf1b","infoHashBuffer":{"type":"Buffer","data":[197,147,125,242,108,36,98,180,163,85,185,112,47,211,181,53,11,83,207,27]},"announce":[],"urlList":[]}}