{"title":"[Pornmegaload][50plusmilfs] 2016-03-17 Mia Morgan - Mia fucks. H","uid":13912803,"size":1324945195,"categoryP":"porn","categoryS":"hd___movies","magnet":"?xt=urn:btih:ca8bbbfcbdd0f726cb660d43b859a7b2d4abf911&amp;dn=%5BPornmegaload%5D%5B50plusmilfs%5D+2016-03-17+Mia+Morgan+-+Mia+fucks.+H&amp;tr=udp%3A%2F%2Ftracker.leechers-paradise.org%3A6969&amp;tr=udp%3A%2F%2Fzer0day.ch%3A1337&amp;tr=udp%3A%2F%2Fopen.demonii.com%3A1337&amp;tr=udp%3A%2F%2Ftracker.coppersurfer.tk%3A6969&amp;tr=udp%3A%2F%2Fexodus.desync.com%3A6969","seeders":0,"leechers":0,"uploader":"Piratepr0n","files":1,"time":1458316429,"description":"-------------------------------------------------------------------------------------\nName:\n[Pornmegaload][50plusmilfs] 2016-03-17 Mia Morgan - Mia fucks. Her hubby watches. [MP4][1920x1080]\n-------------------------------------------------------------------------------------\nFile list:\npml.16.03.17.mia.morgan.mia.fucks.her.hubby.watches.mp4 (1.23 GiB | 1920x1080 | 21min 47s | MPEG-4) \nhttp://imgfapper.com/img-56ec1677ece2e.html","torrent":{"xt":"urn:btih:ca8bbbfcbdd0f726cb660d43b859a7b2d4abf911","amp;dn":"%5BPornmegaload%5D%5B50plusmilfs%5D+2016-03-17+Mia+Morgan+-+Mia+fucks.+H","amp;tr":["udp%3A%2F%2Ftracker.leechers-paradise.org%3A6969","udp%3A%2F%2Fzer0day.ch%3A1337","udp%3A%2F%2Fopen.demonii.com%3A1337","udp%3A%2F%2Ftracker.coppersurfer.tk%3A6969","udp%3A%2F%2Fexodus.desync.com%3A6969"],"infoHash":"ca8bbbfcbdd0f726cb660d43b859a7b2d4abf911","infoHashBuffer":{"type":"Buffer","data":[202,139,187,252,189,208,247,38,203,102,13,67,184,89,167,178,212,171,249,17]},"announce":[],"urlList":[]}}