{"title":"DigitalPlayground.16.03.07.Sadie.Blair.And.Sandy.Fantasy.Lipstic","uid":13793775,"size":355018994,"categoryP":"porn","categoryS":"movie_clips","magnet":"?xt=urn:btih:cf558e7d3d5df5b00cc569d5795142f11bc7b74a&amp;dn=DigitalPlayground.16.03.07.Sadie.Blair.And.Sandy.Fantasy.Lipstic&amp;tr=udp%3A%2F%2Ftracker.leechers-paradise.org%3A6969&amp;tr=udp%3A%2F%2Fzer0day.ch%3A1337&amp;tr=udp%3A%2F%2Fopen.demonii.com%3A1337&amp;tr=udp%3A%2F%2Ftracker.coppersurfer.tk%3A6969&amp;tr=udp%3A%2F%2Fexodus.desync.com%3A6969","seeders":0,"leechers":1,"uploader":"Piratepr0n","files":1,"time":1457404287,"description":"-------------------------------------------------------------------------------------\nName:\nDigitalPlayground.16.03.07.Sadie.Blair.And.Sandy.Fantasy.Lipstick.Lesbians.XXX.SD\n-------------------------------------------------------------------------------------\nFile list:\nDigitalPlayground.16.03.07.Sadie.Blair.And.Sandy.Fantasy.Lipstick.Lesbians.XXX.SD.MP4-RARBG.mp4 (339 MiB | 720x400 | 41min 11s | MPEG-4) \nhttp://imgfapper.com/img-56de2b66c7374.html","torrent":{"xt":"urn:btih:cf558e7d3d5df5b00cc569d5795142f11bc7b74a","amp;dn":"DigitalPlayground.16.03.07.Sadie.Blair.And.Sandy.Fantasy.Lipstic","amp;tr":["udp%3A%2F%2Ftracker.leechers-paradise.org%3A6969","udp%3A%2F%2Fzer0day.ch%3A1337","udp%3A%2F%2Fopen.demonii.com%3A1337","udp%3A%2F%2Ftracker.coppersurfer.tk%3A6969","udp%3A%2F%2Fexodus.desync.com%3A6969"],"infoHash":"cf558e7d3d5df5b00cc569d5795142f11bc7b74a","infoHashBuffer":{"type":"Buffer","data":[207,85,142,125,61,93,245,176,12,197,105,213,121,81,66,241,27,199,183,74]},"announce":[],"urlList":[]}}