{"title":"Revista Clara 04-16","uid":13972895,"size":16426770,"categoryP":"other","categoryS":"other","magnet":"?xt=urn:btih:d25905ac072402453fd72f57bb8a43758c7baccf&amp;dn=Revista+Clara+04-16&amp;tr=udp%3A%2F%2Ftracker.leechers-paradise.org%3A6969&amp;tr=udp%3A%2F%2Fzer0day.ch%3A1337&amp;tr=udp%3A%2F%2Fopen.demonii.com%3A1337&amp;tr=udp%3A%2F%2Ftracker.coppersurfer.tk%3A6969&amp;tr=udp%3A%2F%2Fexodus.desync.com%3A6969","seeders":0,"leechers":0,"uploader":"virana","files":1,"time":1458629986,"description":"Clara/Abril 2016 &quot;Especial cocina Ligera más Sabor y Menos Kcal&quot;","torrent":{"xt":"urn:btih:d25905ac072402453fd72f57bb8a43758c7baccf","amp;dn":"Revista+Clara+04-16","amp;tr":["udp%3A%2F%2Ftracker.leechers-paradise.org%3A6969","udp%3A%2F%2Fzer0day.ch%3A1337","udp%3A%2F%2Fopen.demonii.com%3A1337","udp%3A%2F%2Ftracker.coppersurfer.tk%3A6969","udp%3A%2F%2Fexodus.desync.com%3A6969"],"infoHash":"d25905ac072402453fd72f57bb8a43758c7baccf","infoHashBuffer":{"type":"Buffer","data":[210,89,5,172,7,36,2,69,63,215,47,87,187,138,67,117,140,123,172,207]},"announce":[],"urlList":[]}}