{"title":"Holby.City.S18E24.Who.You.Are.XviD-AFG","uid":13980572,"size":522560000,"categoryP":"video","categoryS":"tv_shows","magnet":"?xt=urn:btih:da4289573b2da005327dd51c6fe1cae1ea968ec4&amp;dn=Holby.City.S18E24.Who.You.Are.XviD-AFG&amp;tr=udp%3A%2F%2Ftracker.leechers-paradise.org%3A6969&amp;tr=udp%3A%2F%2Fzer0day.ch%3A1337&amp;tr=udp%3A%2F%2Fopen.demonii.com%3A1337&amp;tr=udp%3A%2F%2Ftracker.coppersurfer.tk%3A6969&amp;tr=udp%3A%2F%2Fexodus.desync.com%3A6969","seeders":0,"leechers":0,"uploader":"TvTeam","files":12,"time":1458685152,"description":"https://www.torrenting.com\r\n\r\nSign up is OPEN - for time being. Come and have fun.\r\n\r\n------------------------------------------------------------------------\r\n\r\nReNEW our seedbox by donating bitcoin To: 1N1qWp6Hk1REFXgJ8yviqCnLsn76BfXFh1","torrent":{"xt":"urn:btih:da4289573b2da005327dd51c6fe1cae1ea968ec4","amp;dn":"Holby.City.S18E24.Who.You.Are.XviD-AFG","amp;tr":["udp%3A%2F%2Ftracker.leechers-paradise.org%3A6969","udp%3A%2F%2Fzer0day.ch%3A1337","udp%3A%2F%2Fopen.demonii.com%3A1337","udp%3A%2F%2Ftracker.coppersurfer.tk%3A6969","udp%3A%2F%2Fexodus.desync.com%3A6969"],"infoHash":"da4289573b2da005327dd51c6fe1cae1ea968ec4","infoHashBuffer":{"type":"Buffer","data":[218,66,137,87,59,45,160,5,50,125,213,28,111,225,202,225,234,150,142,196]},"announce":[],"urlList":[]}}