{"title":"Sibel Kekilli Cumshot Compilation","uid":13932987,"size":93267792,"categoryP":"porn","categoryS":"movie_clips","magnet":"?xt=urn:btih:e0d454dc69a70b538bb30577727bc6c0818fc2f4&amp;dn=Sibel+Kekilli+Cumshot+Compilation+PIR%40TE&amp;tr=udp%3A%2F%2Ftracker.leechers-paradise.org%3A6969&amp;tr=udp%3A%2F%2Fzer0day.ch%3A1337&amp;tr=udp%3A%2F%2Fopen.demonii.com%3A1337&amp;tr=udp%3A%2F%2Ftracker.coppersurfer.tk%3A6969&amp;tr=udp%3A%2F%2Fexodus.desync.com%3A6969","seeders":0,"leechers":1,"uploader":"Piratepr0n","files":1,"time":1458431052,"description":"-------------------------------------------------------------------------------------\nName:\nSibel Kekilli Cumshot Compilation   \n  --------------------\nFile list:\nSibel Kekilli Cumshot Compilation    (88.9 MiB | 720x406 | 21min 41s | MPEG-4) \nhttp://imgfapper.com/img-56edd634242d2.html","torrent":{"xt":"urn:btih:e0d454dc69a70b538bb30577727bc6c0818fc2f4","amp;dn":"Sibel+Kekilli+Cumshot+Compilation+PIR%40TE","amp;tr":["udp%3A%2F%2Ftracker.leechers-paradise.org%3A6969","udp%3A%2F%2Fzer0day.ch%3A1337","udp%3A%2F%2Fopen.demonii.com%3A1337","udp%3A%2F%2Ftracker.coppersurfer.tk%3A6969","udp%3A%2F%2Fexodus.desync.com%3A6969"],"infoHash":"e0d454dc69a70b538bb30577727bc6c0818fc2f4","infoHashBuffer":{"type":"Buffer","data":[224,212,84,220,105,167,11,83,139,179,5,119,114,123,198,192,129,143,194,244]},"announce":[],"urlList":[]}}