{"title":"Violent.Shit.The.Movie.2015.480p.x264-mSD","uid":13944033,"size":372380126,"categoryP":"video","categoryS":"movies","magnet":"?xt=urn:btih:e17abf662101a9a70c00f47f4a3634a0238b9fc3&amp;dn=Violent.Shit.The.Movie.2015.480p.x264-mSD&amp;tr=udp%3A%2F%2Ftracker.leechers-paradise.org%3A6969&amp;tr=udp%3A%2F%2Fzer0day.ch%3A1337&amp;tr=udp%3A%2F%2Fopen.demonii.com%3A1337&amp;tr=udp%3A%2F%2Ftracker.coppersurfer.tk%3A6969&amp;tr=udp%3A%2F%2Fexodus.desync.com%3A6969","seeders":0,"leechers":0,"uploader":"TvTeam","files":12,"time":1458492103,"description":"https://www.torrenting.com\r\n\r\nSign up is OPEN - for the time being. Come and have fun.\r\n\r\n-----\r\n\r\nReNEW our seedbox by donating bitcoin To: 1N1qWp6Hk1REFXgJ8yviqCnLsn76BfXFh1","torrent":{"xt":"urn:btih:e17abf662101a9a70c00f47f4a3634a0238b9fc3","amp;dn":"Violent.Shit.The.Movie.2015.480p.x264-mSD","amp;tr":["udp%3A%2F%2Ftracker.leechers-paradise.org%3A6969","udp%3A%2F%2Fzer0day.ch%3A1337","udp%3A%2F%2Fopen.demonii.com%3A1337","udp%3A%2F%2Ftracker.coppersurfer.tk%3A6969","udp%3A%2F%2Fexodus.desync.com%3A6969"],"infoHash":"e17abf662101a9a70c00f47f4a3634a0238b9fc3","infoHashBuffer":{"type":"Buffer","data":[225,122,191,102,33,1,169,167,12,0,244,127,74,54,52,160,35,139,159,195]},"announce":[],"urlList":[]}}