{"title":"Slut Training 2","uid":13602106,"size":1830120147,"categoryP":"porn","categoryS":"movies","magnet":"?xt=urn:btih:e85283bb62fb534e296b32614cb08d70aede6cac&amp;dn=Slut+Training+2&amp;tr=udp%3A%2F%2Ftracker.leechers-paradise.org%3A6969&amp;tr=udp%3A%2F%2Fzer0day.ch%3A1337&amp;tr=udp%3A%2F%2Fopen.demonii.com%3A1337&amp;tr=udp%3A%2F%2Ftracker.coppersurfer.tk%3A6969&amp;tr=udp%3A%2F%2Fexodus.desync.com%3A6969","seeders":0,"leechers":0,"uploader":"angel_799","files":2,"time":1455873786,"description":"Screens:http://picangel.com/?g=754287\r\n-----------------------------------------------------------\r\nIf you like this torrent, please post a comment!\r\n\r\nPlease Seed the have for others","torrent":{"xt":"urn:btih:e85283bb62fb534e296b32614cb08d70aede6cac","amp;dn":"Slut+Training+2","amp;tr":["udp%3A%2F%2Ftracker.leechers-paradise.org%3A6969","udp%3A%2F%2Fzer0day.ch%3A1337","udp%3A%2F%2Fopen.demonii.com%3A1337","udp%3A%2F%2Ftracker.coppersurfer.tk%3A6969","udp%3A%2F%2Fexodus.desync.com%3A6969"],"infoHash":"e85283bb62fb534e296b32614cb08d70aede6cac","infoHashBuffer":{"type":"Buffer","data":[232,82,131,187,98,251,83,78,41,107,50,97,76,176,141,112,174,222,108,172]},"announce":[],"urlList":[]}}